<annotation>
	<folder>seals</folder>
	<filename>438_33.jpg</filename>
	<source>
		<database>Source</database>
	</source>
	<size>
		<width>544</width>
		<height>544</height>
		<depth>3</depth>
	</size>
	<segmented>0</segmented>
	<object>
		<name>seals</name>
		<pose>Unspecified</pose>
		<truncated>0</truncated>
		<difficult>0</difficult>
		<bndbox>
			<xmin>278.0</xmin>
			<ymin>98.0</ymin>
			<xmax>378.0</xmax>
			<ymax>198.0</ymax>
		</bndbox>
	</object>
	<object>
		<name>seals</name>
		<pose>Unspecified</pose>
		<truncated>0</truncated>
		<difficult>0</difficult>
		<bndbox>
			<xmin>424.0</xmin>
			<ymin>26.0</ymin>
			<xmax>494.0</xmax>
			<ymax>96.0</ymax>
		</bndbox>
	</object>
	<object>
		<name>seals</name>
		<pose>Unspecified</pose>
		<truncated>0</truncated>
		<difficult>0</difficult>
		<bndbox>
			<xmin>228.0</xmin>
			<ymin>26.0</ymin>
			<xmax>298.0</xmax>
			<ymax>96.0</ymax>
		</bndbox>
	</object>
	<object>
		<name>seals</name>
		<pose>Unspecified</pose>
		<truncated>0</truncated>
		<difficult>0</difficult>
		<bndbox>
			<xmin>160.0</xmin>
			<ymin>113.0</ymin>
			<xmax>230.0</xmax>
			<ymax>183.0</ymax>
		</bndbox>
	</object>
	<object>
		<name>seals</name>
		<pose>Unspecified</pose>
		<truncated>0</truncated>
		<difficult>0</difficult>
		<bndbox>
			<xmin>441.0</xmin>
			<ymin>131.0</ymin>
			<xmax>511.0</xmax>
			<ymax>201.0</ymax>
		</bndbox>
	</object>
	<object>
		<name>seals</name>
		<pose>Unspecified</pose>
		<truncated>0</truncated>
		<difficult>0</difficult>
		<bndbox>
			<xmin>504.0</xmin>
			<ymin>148.0</ymin>
			<xmax>544.0</xmax>
			<ymax>218.0</ymax>
		</bndbox>
	</object>
	<object>
		<name>seals</name>
		<pose>Unspecified</pose>
		<truncated>0</truncated>
		<difficult>0</difficult>
		<bndbox>
			<xmin>181.0</xmin>
			<ymin>226.0</ymin>
			<xmax>251.0</xmax>
			<ymax>296.0</ymax>
		</bndbox>
	</object>
	<object>
		<name>seals</name>
		<pose>Unspecified</pose>
		<truncated>0</truncated>
		<difficult>0</difficult>
		<bndbox>
			<xmin>131.0</xmin>
			<ymin>230.0</ymin>
			<xmax>201.0</xmax>
			<ymax>300.0</ymax>
		</bndbox>
	</object>
	<object>
		<name>seals</name>
		<pose>Unspecified</pose>
		<truncated>0</truncated>
		<difficult>0</difficult>
		<bndbox>
			<xmin>352.0</xmin>
			<ymin>235.0</ymin>
			<xmax>422.0</xmax>
			<ymax>305.0</ymax>
		</bndbox>
	</object>
	<object>
		<name>seals</name>
		<pose>Unspecified</pose>
		<truncated>0</truncated>
		<difficult>0</difficult>
		<bndbox>
			<xmin>416.0</xmin>
			<ymin>291.0</ymin>
			<xmax>486.0</xmax>
			<ymax>361.0</ymax>
		</bndbox>
	</object>
	<object>
		<name>seals</name>
		<pose>Unspecified</pose>
		<truncated>0</truncated>
		<difficult>0</difficult>
		<bndbox>
			<xmin>428.0</xmin>
			<ymin>348.0</ymin>
			<xmax>498.0</xmax>
			<ymax>418.0</ymax>
		</bndbox>
	</object>
	<object>
		<name>seals</name>
		<pose>Unspecified</pose>
		<truncated>0</truncated>
		<difficult>0</difficult>
		<bndbox>
			<xmin>370.0</xmin>
			<ymin>395.0</ymin>
			<xmax>440.0</xmax>
			<ymax>465.0</ymax>
		</bndbox>
	</object>
	<object>
		<name>seals</name>
		<pose>Unspecified</pose>
		<truncated>0</truncated>
		<difficult>0</difficult>
		<bndbox>
			<xmin>317.0</xmin>
			<ymin>468.0</ymin>
			<xmax>387.0</xmax>
			<ymax>538.0</ymax>
		</bndbox>
	</object></annotation>