<annotation>
	<folder>seals</folder>
	<filename>203_42.jpg</filename>
	<source>
		<database>Source</database>
	</source>
	<size>
		<width>544</width>
		<height>544</height>
		<depth>3</depth>
	</size>
	<segmented>0</segmented>
	<object>
		<name>seals</name>
		<pose>Unspecified</pose>
		<truncated>0</truncated>
		<difficult>0</difficult>
		<bndbox>
			<xmin>146.0</xmin>
			<ymin>26.0</ymin>
			<xmax>256.0</xmax>
			<ymax>136.0</ymax>
		</bndbox>
	</object>
	<object>
		<name>seals</name>
		<pose>Unspecified</pose>
		<truncated>0</truncated>
		<difficult>0</difficult>
		<bndbox>
			<xmin>161.0</xmin>
			<ymin>41.0</ymin>
			<xmax>241.0</xmax>
			<ymax>121.0</ymax>
		</bndbox>
	</object>
	<object>
		<name>seals</name>
		<pose>Unspecified</pose>
		<truncated>0</truncated>
		<difficult>0</difficult>
		<bndbox>
			<xmin>171.0</xmin>
			<ymin>51.0</ymin>
			<xmax>231.0</xmax>
			<ymax>111.0</ymax>
		</bndbox>
	</object>
	<object>
		<name>seals</name>
		<pose>Unspecified</pose>
		<truncated>0</truncated>
		<difficult>0</difficult>
		<bndbox>
			<xmin>203.0</xmin>
			<ymin>343.0</ymin>
			<xmax>313.0</xmax>
			<ymax>453.0</ymax>
		</bndbox>
	</object>
	<object>
		<name>seals</name>
		<pose>Unspecified</pose>
		<truncated>0</truncated>
		<difficult>0</difficult>
		<bndbox>
			<xmin>204.0</xmin>
			<ymin>43.0</ymin>
			<xmax>354.0</xmax>
			<ymax>193.0</ymax>
		</bndbox>
	</object>
	<object>
		<name>seals</name>
		<pose>Unspecified</pose>
		<truncated>0</truncated>
		<difficult>0</difficult>
		<bndbox>
			<xmin>218.0</xmin>
			<ymin>358.0</ymin>
			<xmax>298.0</xmax>
			<ymax>438.0</ymax>
		</bndbox>
	</object>
	<object>
		<name>seals</name>
		<pose>Unspecified</pose>
		<truncated>0</truncated>
		<difficult>0</difficult>
		<bndbox>
			<xmin>224.0</xmin>
			<ymin>63.0</ymin>
			<xmax>334.0</xmax>
			<ymax>173.0</ymax>
		</bndbox>
	</object>
	<object>
		<name>seals</name>
		<pose>Unspecified</pose>
		<truncated>0</truncated>
		<difficult>0</difficult>
		<bndbox>
			<xmin>228.0</xmin>
			<ymin>368.0</ymin>
			<xmax>288.0</xmax>
			<ymax>428.0</ymax>
		</bndbox>
	</object>
	<object>
		<name>seals</name>
		<pose>Unspecified</pose>
		<truncated>0</truncated>
		<difficult>0</difficult>
		<bndbox>
			<xmin>239.0</xmin>
			<ymin>78.0</ymin>
			<xmax>319.0</xmax>
			<ymax>158.0</ymax>
		</bndbox>
	</object>
	<object>
		<name>seals</name>
		<pose>Unspecified</pose>
		<truncated>0</truncated>
		<difficult>0</difficult>
		<bndbox>
			<xmin>247.0</xmin>
			<ymin>0.1</ymin>
			<xmax>357.0</xmax>
			<ymax>108.1</ymax>
		</bndbox>
	</object>
	<object>
		<name>seals</name>
		<pose>Unspecified</pose>
		<truncated>0</truncated>
		<difficult>0</difficult>
		<bndbox>
			<xmin>262.0</xmin>
			<ymin>13.0</ymin>
			<xmax>342.0</xmax>
			<ymax>93.0</ymax>
		</bndbox>
	</object>
	<object>
		<name>seals</name>
		<pose>Unspecified</pose>
		<truncated>0</truncated>
		<difficult>0</difficult>
		<bndbox>
			<xmin>272.0</xmin>
			<ymin>23.0</ymin>
			<xmax>332.0</xmax>
			<ymax>83.0</ymax>
		</bndbox>
	</object>
	<object>
		<name>seals</name>
		<pose>Unspecified</pose>
		<truncated>0</truncated>
		<difficult>0</difficult>
		<bndbox>
			<xmin>282.0</xmin>
			<ymin>70.0</ymin>
			<xmax>392.0</xmax>
			<ymax>180.0</ymax>
		</bndbox>
	</object>
	<object>
		<name>seals</name>
		<pose>Unspecified</pose>
		<truncated>0</truncated>
		<difficult>0</difficult>
		<bndbox>
			<xmin>297.0</xmin>
			<ymin>85.0</ymin>
			<xmax>377.0</xmax>
			<ymax>165.0</ymax>
		</bndbox>
	</object>
	<object>
		<name>seals</name>
		<pose>Unspecified</pose>
		<truncated>0</truncated>
		<difficult>0</difficult>
		<bndbox>
			<xmin>307.0</xmin>
			<ymin>95.0</ymin>
			<xmax>367.0</xmax>
			<ymax>155.0</ymax>
		</bndbox>
	</object>
	<object>
		<name>seals</name>
		<pose>Unspecified</pose>
		<truncated>0</truncated>
		<difficult>0</difficult>
		<bndbox>
			<xmin>362.0</xmin>
			<ymin>299.0</ymin>
			<xmax>472.0</xmax>
			<ymax>409.0</ymax>
		</bndbox>
	</object>
	<object>
		<name>seals</name>
		<pose>Unspecified</pose>
		<truncated>0</truncated>
		<difficult>0</difficult>
		<bndbox>
			<xmin>363.0</xmin>
			<ymin>333.0</ymin>
			<xmax>473.0</xmax>
			<ymax>443.0</ymax>
		</bndbox>
	</object>
	<object>
		<name>seals</name>
		<pose>Unspecified</pose>
		<truncated>0</truncated>
		<difficult>0</difficult>
		<bndbox>
			<xmin>377.0</xmin>
			<ymin>314.0</ymin>
			<xmax>457.0</xmax>
			<ymax>394.0</ymax>
		</bndbox>
	</object>
	<object>
		<name>seals</name>
		<pose>Unspecified</pose>
		<truncated>0</truncated>
		<difficult>0</difficult>
		<bndbox>
			<xmin>378.0</xmin>
			<ymin>348.0</ymin>
			<xmax>458.0</xmax>
			<ymax>428.0</ymax>
		</bndbox>
	</object>
	<object>
		<name>seals</name>
		<pose>Unspecified</pose>
		<truncated>0</truncated>
		<difficult>0</difficult>
		<bndbox>
			<xmin>387.0</xmin>
			<ymin>324.0</ymin>
			<xmax>447.0</xmax>
			<ymax>384.0</ymax>
		</bndbox>
	</object>
	<object>
		<name>seals</name>
		<pose>Unspecified</pose>
		<truncated>0</truncated>
		<difficult>0</difficult>
		<bndbox>
			<xmin>388.0</xmin>
			<ymin>358.0</ymin>
			<xmax>448.0</xmax>
			<ymax>418.0</ymax>
		</bndbox>
	</object>
	<object>
		<name>seals</name>
		<pose>Unspecified</pose>
		<truncated>0</truncated>
		<difficult>0</difficult>
		<bndbox>
			<xmin>421.0</xmin>
			<ymin>308.0</ymin>
			<xmax>531.0</xmax>
			<ymax>418.0</ymax>
		</bndbox>
	</object>
	<object>
		<name>seals</name>
		<pose>Unspecified</pose>
		<truncated>0</truncated>
		<difficult>0</difficult>
		<bndbox>
			<xmin>436.0</xmin>
			<ymin>323.0</ymin>
			<xmax>516.0</xmax>
			<ymax>403.0</ymax>
		</bndbox>
	</object>
	<object>
		<name>seals</name>
		<pose>Unspecified</pose>
		<truncated>0</truncated>
		<difficult>0</difficult>
		<bndbox>
			<xmin>436.0</xmin>
			<ymin>394.0</ymin>
			<xmax>543.9</xmax>
			<ymax>543.9</ymax>
		</bndbox>
	</object>
	<object>
		<name>seals</name>
		<pose>Unspecified</pose>
		<truncated>0</truncated>
		<difficult>0</difficult>
		<bndbox>
			<xmin>441.0</xmin>
			<ymin>40.0</ymin>
			<xmax>543.9</xmax>
			<ymax>150.0</ymax>
		</bndbox>
	</object>
	<object>
		<name>seals</name>
		<pose>Unspecified</pose>
		<truncated>0</truncated>
		<difficult>0</difficult>
		<bndbox>
			<xmin>446.0</xmin>
			<ymin>333.0</ymin>
			<xmax>506.0</xmax>
			<ymax>393.0</ymax>
		</bndbox>
	</object>
	<object>
		<name>seals</name>
		<pose>Unspecified</pose>
		<truncated>0</truncated>
		<difficult>0</difficult>
		<bndbox>
			<xmin>456.0</xmin>
			<ymin>55.0</ymin>
			<xmax>536.0</xmax>
			<ymax>135.0</ymax>
		</bndbox>
	</object>
	<object>
		<name>seals</name>
		<pose>Unspecified</pose>
		<truncated>0</truncated>
		<difficult>0</difficult>
		<bndbox>
			<xmin>456.0</xmin>
			<ymin>309.0</ymin>
			<xmax>543.9</xmax>
			<ymax>419.0</ymax>
		</bndbox>
	</object>
	<object>
		<name>seals</name>
		<pose>Unspecified</pose>
		<truncated>0</truncated>
		<difficult>0</difficult>
		<bndbox>
			<xmin>456.0</xmin>
			<ymin>414.0</ymin>
			<xmax>543.9</xmax>
			<ymax>524.0</ymax>
		</bndbox>
	</object>
	<object>
		<name>seals</name>
		<pose>Unspecified</pose>
		<truncated>0</truncated>
		<difficult>0</difficult>
		<bndbox>
			<xmin>466.0</xmin>
			<ymin>16.0</ymin>
			<xmax>543.9</xmax>
			<ymax>126.0</ymax>
		</bndbox>
	</object>
	<object>
		<name>seals</name>
		<pose>Unspecified</pose>
		<truncated>0</truncated>
		<difficult>0</difficult>
		<bndbox>
			<xmin>466.0</xmin>
			<ymin>65.0</ymin>
			<xmax>526.0</xmax>
			<ymax>125.0</ymax>
		</bndbox>
	</object>
	<object>
		<name>seals</name>
		<pose>Unspecified</pose>
		<truncated>0</truncated>
		<difficult>0</difficult>
		<bndbox>
			<xmin>471.0</xmin>
			<ymin>324.0</ymin>
			<xmax>543.9</xmax>
			<ymax>404.0</ymax>
		</bndbox>
	</object>
	<object>
		<name>seals</name>
		<pose>Unspecified</pose>
		<truncated>0</truncated>
		<difficult>0</difficult>
		<bndbox>
			<xmin>471.0</xmin>
			<ymin>429.0</ymin>
			<xmax>543.9</xmax>
			<ymax>509.0</ymax>
		</bndbox>
	</object>
	<object>
		<name>seals</name>
		<pose>Unspecified</pose>
		<truncated>0</truncated>
		<difficult>0</difficult>
		<bndbox>
			<xmin>476.0</xmin>
			<ymin>40.0</ymin>
			<xmax>543.9</xmax>
			<ymax>150.0</ymax>
		</bndbox>
	</object>
	<object>
		<name>seals</name>
		<pose>Unspecified</pose>
		<truncated>0</truncated>
		<difficult>0</difficult>
		<bndbox>
			<xmin>481.0</xmin>
			<ymin>31.0</ymin>
			<xmax>543.9</xmax>
			<ymax>111.0</ymax>
		</bndbox>
	</object>
	<object>
		<name>seals</name>
		<pose>Unspecified</pose>
		<truncated>0</truncated>
		<difficult>0</difficult>
		<bndbox>
			<xmin>481.0</xmin>
			<ymin>334.0</ymin>
			<xmax>541.0</xmax>
			<ymax>394.0</ymax>
		</bndbox>
	</object>
	<object>
		<name>seals</name>
		<pose>Unspecified</pose>
		<truncated>0</truncated>
		<difficult>0</difficult>
		<bndbox>
			<xmin>491.0</xmin>
			<ymin>41.0</ymin>
			<xmax>543.9</xmax>
			<ymax>101.0</ymax>
		</bndbox>
	</object>
	<object>
		<name>seals</name>
		<pose>Unspecified</pose>
		<truncated>0</truncated>
		<difficult>0</difficult>
		<bndbox>
			<xmin>491.0</xmin>
			<ymin>55.0</ymin>
			<xmax>543.9</xmax>
			<ymax>135.0</ymax>
		</bndbox>
	</object>
	<object>
		<name>seals</name>
		<pose>Unspecified</pose>
		<truncated>0</truncated>
		<difficult>0</difficult>
		<bndbox>
			<xmin>501.0</xmin>
			<ymin>65.0</ymin>
			<xmax>543.9</xmax>
			<ymax>125.0</ymax>
		</bndbox>
	</object></annotation>