<annotation>
	<folder>seals</folder>
	<filename>437_51.jpg</filename>
	<source>
		<database>Source</database>
	</source>
	<size>
		<width>544</width>
		<height>544</height>
		<depth>3</depth>
	</size>
	<segmented>0</segmented>
	<object>
		<name>seals</name>
		<pose>Unspecified</pose>
		<truncated>0</truncated>
		<difficult>0</difficult>
		<bndbox>
			<xmin>0.1</xmin>
			<ymin>258.0</ymin>
			<xmax>40.1</xmax>
			<ymax>308.0</ymax>
		</bndbox>
	</object>
	<object>
		<name>seals</name>
		<pose>Unspecified</pose>
		<truncated>0</truncated>
		<difficult>0</difficult>
		<bndbox>
			<xmin>19.0</xmin>
			<ymin>493.0</ymin>
			<xmax>69.0</xmax>
			<ymax>543.0</ymax>
		</bndbox>
	</object>
	<object>
		<name>seals</name>
		<pose>Unspecified</pose>
		<truncated>0</truncated>
		<difficult>0</difficult>
		<bndbox>
			<xmin>22.0</xmin>
			<ymin>191.0</ymin>
			<xmax>72.0</xmax>
			<ymax>241.0</ymax>
		</bndbox>
	</object>
	<object>
		<name>seals</name>
		<pose>Unspecified</pose>
		<truncated>0</truncated>
		<difficult>0</difficult>
		<bndbox>
			<xmin>60.0</xmin>
			<ymin>392.0</ymin>
			<xmax>110.0</xmax>
			<ymax>442.0</ymax>
		</bndbox>
	</object>
	<object>
		<name>seals</name>
		<pose>Unspecified</pose>
		<truncated>0</truncated>
		<difficult>0</difficult>
		<bndbox>
			<xmin>225.0</xmin>
			<ymin>487.0</ymin>
			<xmax>305.0</xmax>
			<ymax>543.9</ymax>
		</bndbox>
	</object>
	<object>
		<name>seals</name>
		<pose>Unspecified</pose>
		<truncated>0</truncated>
		<difficult>0</difficult>
		<bndbox>
			<xmin>262.0</xmin>
			<ymin>403.0</ymin>
			<xmax>312.0</xmax>
			<ymax>453.0</ymax>
		</bndbox>
	</object>
	<object>
		<name>seals</name>
		<pose>Unspecified</pose>
		<truncated>0</truncated>
		<difficult>0</difficult>
		<bndbox>
			<xmin>343.0</xmin>
			<ymin>168.0</ymin>
			<xmax>393.0</xmax>
			<ymax>218.0</ymax>
		</bndbox>
	</object>
	<object>
		<name>seals</name>
		<pose>Unspecified</pose>
		<truncated>0</truncated>
		<difficult>0</difficult>
		<bndbox>
			<xmin>375.0</xmin>
			<ymin>345.0</ymin>
			<xmax>425.0</xmax>
			<ymax>395.0</ymax>
		</bndbox>
	</object>
	<object>
		<name>seals</name>
		<pose>Unspecified</pose>
		<truncated>0</truncated>
		<difficult>0</difficult>
		<bndbox>
			<xmin>378.0</xmin>
			<ymin>467.0</ymin>
			<xmax>428.0</xmax>
			<ymax>517.0</ymax>
		</bndbox>
	</object>
	<object>
		<name>seals</name>
		<pose>Unspecified</pose>
		<truncated>0</truncated>
		<difficult>0</difficult>
		<bndbox>
			<xmin>493.0</xmin>
			<ymin>401.0</ymin>
			<xmax>543.0</xmax>
			<ymax>451.0</ymax>
		</bndbox>
	</object>
	<object>
		<name>seals</name>
		<pose>Unspecified</pose>
		<truncated>0</truncated>
		<difficult>0</difficult>
		<bndbox>
			<xmin>512.0</xmin>
			<ymin>0.1</ymin>
			<xmax>543.9</xmax>
			<ymax>31.1</ymax>
		</bndbox>
	</object></annotation>