<annotation>
	<folder>seals</folder>
	<filename>77_52.jpg</filename>
	<source>
		<database>Source</database>
	</source>
	<size>
		<width>544</width>
		<height>544</height>
		<depth>3</depth>
	</size>
	<segmented>0</segmented>
	<object>
		<name>seals</name>
		<pose>Unspecified</pose>
		<truncated>0</truncated>
		<difficult>0</difficult>
		<bndbox>
			<xmin>0.1</xmin>
			<ymin>170.0</ymin>
			<xmax>86.1</xmax>
			<ymax>280.0</ymax>
		</bndbox>
	</object>
	<object>
		<name>seals</name>
		<pose>Unspecified</pose>
		<truncated>0</truncated>
		<difficult>0</difficult>
		<bndbox>
			<xmin>0.1</xmin>
			<ymin>185.0</ymin>
			<xmax>71.1</xmax>
			<ymax>265.0</ymax>
		</bndbox>
	</object>
	<object>
		<name>seals</name>
		<pose>Unspecified</pose>
		<truncated>0</truncated>
		<difficult>0</difficult>
		<bndbox>
			<xmin>0.1</xmin>
			<ymin>247.0</ymin>
			<xmax>70.1</xmax>
			<ymax>357.0</ymax>
		</bndbox>
	</object>
	<object>
		<name>seals</name>
		<pose>Unspecified</pose>
		<truncated>0</truncated>
		<difficult>0</difficult>
		<bndbox>
			<xmin>0.1</xmin>
			<ymin>262.0</ymin>
			<xmax>55.1</xmax>
			<ymax>342.0</ymax>
		</bndbox>
	</object>
	<object>
		<name>seals</name>
		<pose>Unspecified</pose>
		<truncated>0</truncated>
		<difficult>0</difficult>
		<bndbox>
			<xmin>0.1</xmin>
			<ymin>272.0</ymin>
			<xmax>45.1</xmax>
			<ymax>332.0</ymax>
		</bndbox>
	</object>
	<object>
		<name>seals</name>
		<pose>Unspecified</pose>
		<truncated>0</truncated>
		<difficult>0</difficult>
		<bndbox>
			<xmin>0.1</xmin>
			<ymin>425.0</ymin>
			<xmax>97.1</xmax>
			<ymax>535.0</ymax>
		</bndbox>
	</object>
	<object>
		<name>seals</name>
		<pose>Unspecified</pose>
		<truncated>0</truncated>
		<difficult>0</difficult>
		<bndbox>
			<xmin>1.0</xmin>
			<ymin>195.0</ymin>
			<xmax>61.0</xmax>
			<ymax>255.0</ymax>
		</bndbox>
	</object>
	<object>
		<name>seals</name>
		<pose>Unspecified</pose>
		<truncated>0</truncated>
		<difficult>0</difficult>
		<bndbox>
			<xmin>2.0</xmin>
			<ymin>440.0</ymin>
			<xmax>82.0</xmax>
			<ymax>520.0</ymax>
		</bndbox>
	</object>
	<object>
		<name>seals</name>
		<pose>Unspecified</pose>
		<truncated>0</truncated>
		<difficult>0</difficult>
		<bndbox>
			<xmin>12.0</xmin>
			<ymin>450.0</ymin>
			<xmax>72.0</xmax>
			<ymax>510.0</ymax>
		</bndbox>
	</object>
	<object>
		<name>seals</name>
		<pose>Unspecified</pose>
		<truncated>0</truncated>
		<difficult>0</difficult>
		<bndbox>
			<xmin>14.0</xmin>
			<ymin>341.0</ymin>
			<xmax>124.0</xmax>
			<ymax>451.0</ymax>
		</bndbox>
	</object>
	<object>
		<name>seals</name>
		<pose>Unspecified</pose>
		<truncated>0</truncated>
		<difficult>0</difficult>
		<bndbox>
			<xmin>17.0</xmin>
			<ymin>255.0</ymin>
			<xmax>127.0</xmax>
			<ymax>365.0</ymax>
		</bndbox>
	</object>
	<object>
		<name>seals</name>
		<pose>Unspecified</pose>
		<truncated>0</truncated>
		<difficult>0</difficult>
		<bndbox>
			<xmin>29.0</xmin>
			<ymin>356.0</ymin>
			<xmax>109.0</xmax>
			<ymax>436.0</ymax>
		</bndbox>
	</object>
	<object>
		<name>seals</name>
		<pose>Unspecified</pose>
		<truncated>0</truncated>
		<difficult>0</difficult>
		<bndbox>
			<xmin>32.0</xmin>
			<ymin>270.0</ymin>
			<xmax>112.0</xmax>
			<ymax>350.0</ymax>
		</bndbox>
	</object>
	<object>
		<name>seals</name>
		<pose>Unspecified</pose>
		<truncated>0</truncated>
		<difficult>0</difficult>
		<bndbox>
			<xmin>35.0</xmin>
			<ymin>184.0</ymin>
			<xmax>145.0</xmax>
			<ymax>294.0</ymax>
		</bndbox>
	</object>
	<object>
		<name>seals</name>
		<pose>Unspecified</pose>
		<truncated>0</truncated>
		<difficult>0</difficult>
		<bndbox>
			<xmin>39.0</xmin>
			<ymin>366.0</ymin>
			<xmax>99.0</xmax>
			<ymax>426.0</ymax>
		</bndbox>
	</object>
	<object>
		<name>seals</name>
		<pose>Unspecified</pose>
		<truncated>0</truncated>
		<difficult>0</difficult>
		<bndbox>
			<xmin>42.0</xmin>
			<ymin>280.0</ymin>
			<xmax>102.0</xmax>
			<ymax>340.0</ymax>
		</bndbox>
	</object>
	<object>
		<name>seals</name>
		<pose>Unspecified</pose>
		<truncated>0</truncated>
		<difficult>0</difficult>
		<bndbox>
			<xmin>50.0</xmin>
			<ymin>199.0</ymin>
			<xmax>130.0</xmax>
			<ymax>279.0</ymax>
		</bndbox>
	</object>
	<object>
		<name>seals</name>
		<pose>Unspecified</pose>
		<truncated>0</truncated>
		<difficult>0</difficult>
		<bndbox>
			<xmin>51.0</xmin>
			<ymin>148.0</ymin>
			<xmax>161.0</xmax>
			<ymax>258.0</ymax>
		</bndbox>
	</object>
	<object>
		<name>seals</name>
		<pose>Unspecified</pose>
		<truncated>0</truncated>
		<difficult>0</difficult>
		<bndbox>
			<xmin>60.0</xmin>
			<ymin>0.1</ymin>
			<xmax>170.0</xmax>
			<ymax>109.1</ymax>
		</bndbox>
	</object>
	<object>
		<name>seals</name>
		<pose>Unspecified</pose>
		<truncated>0</truncated>
		<difficult>0</difficult>
		<bndbox>
			<xmin>60.0</xmin>
			<ymin>209.0</ymin>
			<xmax>120.0</xmax>
			<ymax>269.0</ymax>
		</bndbox>
	</object>
	<object>
		<name>seals</name>
		<pose>Unspecified</pose>
		<truncated>0</truncated>
		<difficult>0</difficult>
		<bndbox>
			<xmin>66.0</xmin>
			<ymin>163.0</ymin>
			<xmax>146.0</xmax>
			<ymax>243.0</ymax>
		</bndbox>
	</object>
	<object>
		<name>seals</name>
		<pose>Unspecified</pose>
		<truncated>0</truncated>
		<difficult>0</difficult>
		<bndbox>
			<xmin>75.0</xmin>
			<ymin>14.0</ymin>
			<xmax>155.0</xmax>
			<ymax>94.0</ymax>
		</bndbox>
	</object>
	<object>
		<name>seals</name>
		<pose>Unspecified</pose>
		<truncated>0</truncated>
		<difficult>0</difficult>
		<bndbox>
			<xmin>76.0</xmin>
			<ymin>173.0</ymin>
			<xmax>136.0</xmax>
			<ymax>233.0</ymax>
		</bndbox>
	</object>
	<object>
		<name>seals</name>
		<pose>Unspecified</pose>
		<truncated>0</truncated>
		<difficult>0</difficult>
		<bndbox>
			<xmin>85.0</xmin>
			<ymin>24.0</ymin>
			<xmax>145.0</xmax>
			<ymax>84.0</ymax>
		</bndbox>
	</object>
	<object>
		<name>seals</name>
		<pose>Unspecified</pose>
		<truncated>0</truncated>
		<difficult>0</difficult>
		<bndbox>
			<xmin>86.0</xmin>
			<ymin>188.0</ymin>
			<xmax>236.0</xmax>
			<ymax>338.0</ymax>
		</bndbox>
	</object>
	<object>
		<name>seals</name>
		<pose>Unspecified</pose>
		<truncated>0</truncated>
		<difficult>0</difficult>
		<bndbox>
			<xmin>106.0</xmin>
			<ymin>208.0</ymin>
			<xmax>216.0</xmax>
			<ymax>318.0</ymax>
		</bndbox>
	</object>
	<object>
		<name>seals</name>
		<pose>Unspecified</pose>
		<truncated>0</truncated>
		<difficult>0</difficult>
		<bndbox>
			<xmin>106.0</xmin>
			<ymin>362.0</ymin>
			<xmax>216.0</xmax>
			<ymax>472.0</ymax>
		</bndbox>
	</object>
	<object>
		<name>seals</name>
		<pose>Unspecified</pose>
		<truncated>0</truncated>
		<difficult>0</difficult>
		<bndbox>
			<xmin>121.0</xmin>
			<ymin>223.0</ymin>
			<xmax>201.0</xmax>
			<ymax>303.0</ymax>
		</bndbox>
	</object>
	<object>
		<name>seals</name>
		<pose>Unspecified</pose>
		<truncated>0</truncated>
		<difficult>0</difficult>
		<bndbox>
			<xmin>121.0</xmin>
			<ymin>377.0</ymin>
			<xmax>201.0</xmax>
			<ymax>457.0</ymax>
		</bndbox>
	</object>
	<object>
		<name>seals</name>
		<pose>Unspecified</pose>
		<truncated>0</truncated>
		<difficult>0</difficult>
		<bndbox>
			<xmin>131.0</xmin>
			<ymin>387.0</ymin>
			<xmax>191.0</xmax>
			<ymax>447.0</ymax>
		</bndbox>
	</object>
	<object>
		<name>seals</name>
		<pose>Unspecified</pose>
		<truncated>0</truncated>
		<difficult>0</difficult>
		<bndbox>
			<xmin>159.0</xmin>
			<ymin>53.0</ymin>
			<xmax>269.0</xmax>
			<ymax>163.0</ymax>
		</bndbox>
	</object>
	<object>
		<name>seals</name>
		<pose>Unspecified</pose>
		<truncated>0</truncated>
		<difficult>0</difficult>
		<bndbox>
			<xmin>161.0</xmin>
			<ymin>279.0</ymin>
			<xmax>271.0</xmax>
			<ymax>389.0</ymax>
		</bndbox>
	</object>
	<object>
		<name>seals</name>
		<pose>Unspecified</pose>
		<truncated>0</truncated>
		<difficult>0</difficult>
		<bndbox>
			<xmin>174.0</xmin>
			<ymin>68.0</ymin>
			<xmax>254.0</xmax>
			<ymax>148.0</ymax>
		</bndbox>
	</object>
	<object>
		<name>seals</name>
		<pose>Unspecified</pose>
		<truncated>0</truncated>
		<difficult>0</difficult>
		<bndbox>
			<xmin>176.0</xmin>
			<ymin>294.0</ymin>
			<xmax>256.0</xmax>
			<ymax>374.0</ymax>
		</bndbox>
	</object>
	<object>
		<name>seals</name>
		<pose>Unspecified</pose>
		<truncated>0</truncated>
		<difficult>0</difficult>
		<bndbox>
			<xmin>184.0</xmin>
			<ymin>78.0</ymin>
			<xmax>244.0</xmax>
			<ymax>138.0</ymax>
		</bndbox>
	</object>
	<object>
		<name>seals</name>
		<pose>Unspecified</pose>
		<truncated>0</truncated>
		<difficult>0</difficult>
		<bndbox>
			<xmin>186.0</xmin>
			<ymin>304.0</ymin>
			<xmax>246.0</xmax>
			<ymax>364.0</ymax>
		</bndbox>
	</object>
	<object>
		<name>seals</name>
		<pose>Unspecified</pose>
		<truncated>0</truncated>
		<difficult>0</difficult>
		<bndbox>
			<xmin>307.0</xmin>
			<ymin>232.0</ymin>
			<xmax>417.0</xmax>
			<ymax>342.0</ymax>
		</bndbox>
	</object>
	<object>
		<name>seals</name>
		<pose>Unspecified</pose>
		<truncated>0</truncated>
		<difficult>0</difficult>
		<bndbox>
			<xmin>322.0</xmin>
			<ymin>247.0</ymin>
			<xmax>402.0</xmax>
			<ymax>327.0</ymax>
		</bndbox>
	</object>
	<object>
		<name>seals</name>
		<pose>Unspecified</pose>
		<truncated>0</truncated>
		<difficult>0</difficult>
		<bndbox>
			<xmin>329.0</xmin>
			<ymin>77.0</ymin>
			<xmax>439.0</xmax>
			<ymax>187.0</ymax>
		</bndbox>
	</object>
	<object>
		<name>seals</name>
		<pose>Unspecified</pose>
		<truncated>0</truncated>
		<difficult>0</difficult>
		<bndbox>
			<xmin>332.0</xmin>
			<ymin>257.0</ymin>
			<xmax>392.0</xmax>
			<ymax>317.0</ymax>
		</bndbox>
	</object>
	<object>
		<name>seals</name>
		<pose>Unspecified</pose>
		<truncated>0</truncated>
		<difficult>0</difficult>
		<bndbox>
			<xmin>344.0</xmin>
			<ymin>92.0</ymin>
			<xmax>424.0</xmax>
			<ymax>172.0</ymax>
		</bndbox>
	</object>
	<object>
		<name>seals</name>
		<pose>Unspecified</pose>
		<truncated>0</truncated>
		<difficult>0</difficult>
		<bndbox>
			<xmin>346.0</xmin>
			<ymin>416.0</ymin>
			<xmax>456.0</xmax>
			<ymax>526.0</ymax>
		</bndbox>
	</object>
	<object>
		<name>seals</name>
		<pose>Unspecified</pose>
		<truncated>0</truncated>
		<difficult>0</difficult>
		<bndbox>
			<xmin>354.0</xmin>
			<ymin>102.0</ymin>
			<xmax>414.0</xmax>
			<ymax>162.0</ymax>
		</bndbox>
	</object>
	<object>
		<name>seals</name>
		<pose>Unspecified</pose>
		<truncated>0</truncated>
		<difficult>0</difficult>
		<bndbox>
			<xmin>361.0</xmin>
			<ymin>431.0</ymin>
			<xmax>441.0</xmax>
			<ymax>511.0</ymax>
		</bndbox>
	</object>
	<object>
		<name>seals</name>
		<pose>Unspecified</pose>
		<truncated>0</truncated>
		<difficult>0</difficult>
		<bndbox>
			<xmin>371.0</xmin>
			<ymin>441.0</ymin>
			<xmax>431.0</xmax>
			<ymax>501.0</ymax>
		</bndbox>
	</object>
	<object>
		<name>seals</name>
		<pose>Unspecified</pose>
		<truncated>0</truncated>
		<difficult>0</difficult>
		<bndbox>
			<xmin>456.0</xmin>
			<ymin>212.0</ymin>
			<xmax>543.9</xmax>
			<ymax>362.0</ymax>
		</bndbox>
	</object>
	<object>
		<name>seals</name>
		<pose>Unspecified</pose>
		<truncated>0</truncated>
		<difficult>0</difficult>
		<bndbox>
			<xmin>476.0</xmin>
			<ymin>232.0</ymin>
			<xmax>543.9</xmax>
			<ymax>342.0</ymax>
		</bndbox>
	</object>
	<object>
		<name>seals</name>
		<pose>Unspecified</pose>
		<truncated>0</truncated>
		<difficult>0</difficult>
		<bndbox>
			<xmin>491.0</xmin>
			<ymin>247.0</ymin>
			<xmax>543.9</xmax>
			<ymax>327.0</ymax>
		</bndbox>
	</object></annotation>