<annotation>
	<folder>seals</folder>
	<filename>96_52.jpg</filename>
	<source>
		<database>Source</database>
	</source>
	<size>
		<width>544</width>
		<height>544</height>
		<depth>3</depth>
	</size>
	<segmented>0</segmented>
	<object>
		<name>seals</name>
		<pose>Unspecified</pose>
		<truncated>0</truncated>
		<difficult>0</difficult>
		<bndbox>
			<xmin>0.1</xmin>
			<ymin>147.0</ymin>
			<xmax>41.1</xmax>
			<ymax>197.0</ymax>
		</bndbox>
	</object>
	<object>
		<name>seals</name>
		<pose>Unspecified</pose>
		<truncated>0</truncated>
		<difficult>0</difficult>
		<bndbox>
			<xmin>17.0</xmin>
			<ymin>150.0</ymin>
			<xmax>67.0</xmax>
			<ymax>200.0</ymax>
		</bndbox>
	</object>
	<object>
		<name>seals</name>
		<pose>Unspecified</pose>
		<truncated>0</truncated>
		<difficult>0</difficult>
		<bndbox>
			<xmin>18.0</xmin>
			<ymin>148.0</ymin>
			<xmax>98.0</xmax>
			<ymax>228.0</ymax>
		</bndbox>
	</object>
	<object>
		<name>seals</name>
		<pose>Unspecified</pose>
		<truncated>0</truncated>
		<difficult>0</difficult>
		<bndbox>
			<xmin>41.0</xmin>
			<ymin>187.0</ymin>
			<xmax>91.0</xmax>
			<ymax>237.0</ymax>
		</bndbox>
	</object>
	<object>
		<name>seals</name>
		<pose>Unspecified</pose>
		<truncated>0</truncated>
		<difficult>0</difficult>
		<bndbox>
			<xmin>68.0</xmin>
			<ymin>110.0</ymin>
			<xmax>118.0</xmax>
			<ymax>160.0</ymax>
		</bndbox>
	</object>
	<object>
		<name>seals</name>
		<pose>Unspecified</pose>
		<truncated>0</truncated>
		<difficult>0</difficult>
		<bndbox>
			<xmin>78.0</xmin>
			<ymin>193.0</ymin>
			<xmax>128.0</xmax>
			<ymax>243.0</ymax>
		</bndbox>
	</object>
	<object>
		<name>seals</name>
		<pose>Unspecified</pose>
		<truncated>0</truncated>
		<difficult>0</difficult>
		<bndbox>
			<xmin>85.0</xmin>
			<ymin>79.0</ymin>
			<xmax>135.0</xmax>
			<ymax>129.0</ymax>
		</bndbox>
	</object>
	<object>
		<name>seals</name>
		<pose>Unspecified</pose>
		<truncated>0</truncated>
		<difficult>0</difficult>
		<bndbox>
			<xmin>96.0</xmin>
			<ymin>119.0</ymin>
			<xmax>146.0</xmax>
			<ymax>169.0</ymax>
		</bndbox>
	</object>
	<object>
		<name>seals</name>
		<pose>Unspecified</pose>
		<truncated>0</truncated>
		<difficult>0</difficult>
		<bndbox>
			<xmin>99.0</xmin>
			<ymin>0.1</ymin>
			<xmax>149.0</xmax>
			<ymax>32.1</ymax>
		</bndbox>
	</object>
	<object>
		<name>seals</name>
		<pose>Unspecified</pose>
		<truncated>0</truncated>
		<difficult>0</difficult>
		<bndbox>
			<xmin>103.0</xmin>
			<ymin>35.0</ymin>
			<xmax>153.0</xmax>
			<ymax>85.0</ymax>
		</bndbox>
	</object>
	<object>
		<name>seals</name>
		<pose>Unspecified</pose>
		<truncated>0</truncated>
		<difficult>0</difficult>
		<bndbox>
			<xmin>103.0</xmin>
			<ymin>119.0</ymin>
			<xmax>153.0</xmax>
			<ymax>169.0</ymax>
		</bndbox>
	</object>
	<object>
		<name>seals</name>
		<pose>Unspecified</pose>
		<truncated>0</truncated>
		<difficult>0</difficult>
		<bndbox>
			<xmin>105.0</xmin>
			<ymin>204.0</ymin>
			<xmax>155.0</xmax>
			<ymax>254.0</ymax>
		</bndbox>
	</object>
	<object>
		<name>seals</name>
		<pose>Unspecified</pose>
		<truncated>0</truncated>
		<difficult>0</difficult>
		<bndbox>
			<xmin>124.0</xmin>
			<ymin>149.0</ymin>
			<xmax>174.0</xmax>
			<ymax>199.0</ymax>
		</bndbox>
	</object>
	<object>
		<name>seals</name>
		<pose>Unspecified</pose>
		<truncated>0</truncated>
		<difficult>0</difficult>
		<bndbox>
			<xmin>125.0</xmin>
			<ymin>0.1</ymin>
			<xmax>175.0</xmax>
			<ymax>49.1</ymax>
		</bndbox>
	</object>
	<object>
		<name>seals</name>
		<pose>Unspecified</pose>
		<truncated>0</truncated>
		<difficult>0</difficult>
		<bndbox>
			<xmin>131.0</xmin>
			<ymin>61.0</ymin>
			<xmax>211.0</xmax>
			<ymax>141.0</ymax>
		</bndbox>
	</object>
	<object>
		<name>seals</name>
		<pose>Unspecified</pose>
		<truncated>0</truncated>
		<difficult>0</difficult>
		<bndbox>
			<xmin>146.0</xmin>
			<ymin>0.1</ymin>
			<xmax>196.0</xmax>
			<ymax>28.1</ymax>
		</bndbox>
	</object>
	<object>
		<name>seals</name>
		<pose>Unspecified</pose>
		<truncated>0</truncated>
		<difficult>0</difficult>
		<bndbox>
			<xmin>159.0</xmin>
			<ymin>233.0</ymin>
			<xmax>209.0</xmax>
			<ymax>283.0</ymax>
		</bndbox>
	</object>
	<object>
		<name>seals</name>
		<pose>Unspecified</pose>
		<truncated>0</truncated>
		<difficult>0</difficult>
		<bndbox>
			<xmin>168.0</xmin>
			<ymin>121.0</ymin>
			<xmax>218.0</xmax>
			<ymax>171.0</ymax>
		</bndbox>
	</object>
	<object>
		<name>seals</name>
		<pose>Unspecified</pose>
		<truncated>0</truncated>
		<difficult>0</difficult>
		<bndbox>
			<xmin>184.0</xmin>
			<ymin>52.0</ymin>
			<xmax>234.0</xmax>
			<ymax>102.0</ymax>
		</bndbox>
	</object>
	<object>
		<name>seals</name>
		<pose>Unspecified</pose>
		<truncated>0</truncated>
		<difficult>0</difficult>
		<bndbox>
			<xmin>199.0</xmin>
			<ymin>171.0</ymin>
			<xmax>249.0</xmax>
			<ymax>221.0</ymax>
		</bndbox>
	</object>
	<object>
		<name>seals</name>
		<pose>Unspecified</pose>
		<truncated>0</truncated>
		<difficult>0</difficult>
		<bndbox>
			<xmin>202.0</xmin>
			<ymin>140.0</ymin>
			<xmax>252.0</xmax>
			<ymax>190.0</ymax>
		</bndbox>
	</object>
	<object>
		<name>seals</name>
		<pose>Unspecified</pose>
		<truncated>0</truncated>
		<difficult>0</difficult>
		<bndbox>
			<xmin>203.0</xmin>
			<ymin>123.0</ymin>
			<xmax>253.0</xmax>
			<ymax>173.0</ymax>
		</bndbox>
	</object>
	<object>
		<name>seals</name>
		<pose>Unspecified</pose>
		<truncated>0</truncated>
		<difficult>0</difficult>
		<bndbox>
			<xmin>207.0</xmin>
			<ymin>108.0</ymin>
			<xmax>257.0</xmax>
			<ymax>158.0</ymax>
		</bndbox>
	</object>
	<object>
		<name>seals</name>
		<pose>Unspecified</pose>
		<truncated>0</truncated>
		<difficult>0</difficult>
		<bndbox>
			<xmin>209.0</xmin>
			<ymin>0.1</ymin>
			<xmax>259.0</xmax>
			<ymax>29.1</ymax>
		</bndbox>
	</object>
	<object>
		<name>seals</name>
		<pose>Unspecified</pose>
		<truncated>0</truncated>
		<difficult>0</difficult>
		<bndbox>
			<xmin>213.0</xmin>
			<ymin>136.0</ymin>
			<xmax>263.0</xmax>
			<ymax>186.0</ymax>
		</bndbox>
	</object>
	<object>
		<name>seals</name>
		<pose>Unspecified</pose>
		<truncated>0</truncated>
		<difficult>0</difficult>
		<bndbox>
			<xmin>214.0</xmin>
			<ymin>90.0</ymin>
			<xmax>264.0</xmax>
			<ymax>140.0</ymax>
		</bndbox>
	</object>
	<object>
		<name>seals</name>
		<pose>Unspecified</pose>
		<truncated>0</truncated>
		<difficult>0</difficult>
		<bndbox>
			<xmin>214.0</xmin>
			<ymin>206.0</ymin>
			<xmax>264.0</xmax>
			<ymax>256.0</ymax>
		</bndbox>
	</object>
	<object>
		<name>seals</name>
		<pose>Unspecified</pose>
		<truncated>0</truncated>
		<difficult>0</difficult>
		<bndbox>
			<xmin>226.0</xmin>
			<ymin>239.0</ymin>
			<xmax>276.0</xmax>
			<ymax>289.0</ymax>
		</bndbox>
	</object>
	<object>
		<name>seals</name>
		<pose>Unspecified</pose>
		<truncated>0</truncated>
		<difficult>0</difficult>
		<bndbox>
			<xmin>230.0</xmin>
			<ymin>270.0</ymin>
			<xmax>280.0</xmax>
			<ymax>320.0</ymax>
		</bndbox>
	</object>
	<object>
		<name>seals</name>
		<pose>Unspecified</pose>
		<truncated>0</truncated>
		<difficult>0</difficult>
		<bndbox>
			<xmin>232.0</xmin>
			<ymin>0.1</ymin>
			<xmax>282.0</xmax>
			<ymax>27.1</ymax>
		</bndbox>
	</object>
	<object>
		<name>seals</name>
		<pose>Unspecified</pose>
		<truncated>0</truncated>
		<difficult>0</difficult>
		<bndbox>
			<xmin>235.0</xmin>
			<ymin>17.0</ymin>
			<xmax>285.0</xmax>
			<ymax>67.0</ymax>
		</bndbox>
	</object>
	<object>
		<name>seals</name>
		<pose>Unspecified</pose>
		<truncated>0</truncated>
		<difficult>0</difficult>
		<bndbox>
			<xmin>245.0</xmin>
			<ymin>63.0</ymin>
			<xmax>295.0</xmax>
			<ymax>113.0</ymax>
		</bndbox>
	</object>
	<object>
		<name>seals</name>
		<pose>Unspecified</pose>
		<truncated>0</truncated>
		<difficult>0</difficult>
		<bndbox>
			<xmin>252.0</xmin>
			<ymin>216.0</ymin>
			<xmax>302.0</xmax>
			<ymax>266.0</ymax>
		</bndbox>
	</object>
	<object>
		<name>seals</name>
		<pose>Unspecified</pose>
		<truncated>0</truncated>
		<difficult>0</difficult>
		<bndbox>
			<xmin>254.0</xmin>
			<ymin>326.0</ymin>
			<xmax>304.0</xmax>
			<ymax>376.0</ymax>
		</bndbox>
	</object>
	<object>
		<name>seals</name>
		<pose>Unspecified</pose>
		<truncated>0</truncated>
		<difficult>0</difficult>
		<bndbox>
			<xmin>262.0</xmin>
			<ymin>23.0</ymin>
			<xmax>312.0</xmax>
			<ymax>73.0</ymax>
		</bndbox>
	</object>
	<object>
		<name>seals</name>
		<pose>Unspecified</pose>
		<truncated>0</truncated>
		<difficult>0</difficult>
		<bndbox>
			<xmin>266.0</xmin>
			<ymin>213.0</ymin>
			<xmax>316.0</xmax>
			<ymax>263.0</ymax>
		</bndbox>
	</object>
	<object>
		<name>seals</name>
		<pose>Unspecified</pose>
		<truncated>0</truncated>
		<difficult>0</difficult>
		<bndbox>
			<xmin>268.0</xmin>
			<ymin>201.0</ymin>
			<xmax>318.0</xmax>
			<ymax>251.0</ymax>
		</bndbox>
	</object>
	<object>
		<name>seals</name>
		<pose>Unspecified</pose>
		<truncated>0</truncated>
		<difficult>0</difficult>
		<bndbox>
			<xmin>272.0</xmin>
			<ymin>0.1</ymin>
			<xmax>322.0</xmax>
			<ymax>41.1</ymax>
		</bndbox>
	</object>
	<object>
		<name>seals</name>
		<pose>Unspecified</pose>
		<truncated>0</truncated>
		<difficult>0</difficult>
		<bndbox>
			<xmin>287.0</xmin>
			<ymin>122.0</ymin>
			<xmax>337.0</xmax>
			<ymax>172.0</ymax>
		</bndbox>
	</object>
	<object>
		<name>seals</name>
		<pose>Unspecified</pose>
		<truncated>0</truncated>
		<difficult>0</difficult>
		<bndbox>
			<xmin>290.0</xmin>
			<ymin>169.0</ymin>
			<xmax>340.0</xmax>
			<ymax>219.0</ymax>
		</bndbox>
	</object>
	<object>
		<name>seals</name>
		<pose>Unspecified</pose>
		<truncated>0</truncated>
		<difficult>0</difficult>
		<bndbox>
			<xmin>292.0</xmin>
			<ymin>319.0</ymin>
			<xmax>342.0</xmax>
			<ymax>369.0</ymax>
		</bndbox>
	</object>
	<object>
		<name>seals</name>
		<pose>Unspecified</pose>
		<truncated>0</truncated>
		<difficult>0</difficult>
		<bndbox>
			<xmin>297.0</xmin>
			<ymin>0.1</ymin>
			<xmax>347.0</xmax>
			<ymax>44.1</ymax>
		</bndbox>
	</object>
	<object>
		<name>seals</name>
		<pose>Unspecified</pose>
		<truncated>0</truncated>
		<difficult>0</difficult>
		<bndbox>
			<xmin>297.0</xmin>
			<ymin>207.0</ymin>
			<xmax>377.0</xmax>
			<ymax>287.0</ymax>
		</bndbox>
	</object>
	<object>
		<name>seals</name>
		<pose>Unspecified</pose>
		<truncated>0</truncated>
		<difficult>0</difficult>
		<bndbox>
			<xmin>299.0</xmin>
			<ymin>82.0</ymin>
			<xmax>349.0</xmax>
			<ymax>132.0</ymax>
		</bndbox>
	</object>
	<object>
		<name>seals</name>
		<pose>Unspecified</pose>
		<truncated>0</truncated>
		<difficult>0</difficult>
		<bndbox>
			<xmin>302.0</xmin>
			<ymin>157.0</ymin>
			<xmax>352.0</xmax>
			<ymax>207.0</ymax>
		</bndbox>
	</object>
	<object>
		<name>seals</name>
		<pose>Unspecified</pose>
		<truncated>0</truncated>
		<difficult>0</difficult>
		<bndbox>
			<xmin>303.0</xmin>
			<ymin>265.0</ymin>
			<xmax>353.0</xmax>
			<ymax>315.0</ymax>
		</bndbox>
	</object>
	<object>
		<name>seals</name>
		<pose>Unspecified</pose>
		<truncated>0</truncated>
		<difficult>0</difficult>
		<bndbox>
			<xmin>319.0</xmin>
			<ymin>3.0</ymin>
			<xmax>369.0</xmax>
			<ymax>53.0</ymax>
		</bndbox>
	</object>
	<object>
		<name>seals</name>
		<pose>Unspecified</pose>
		<truncated>0</truncated>
		<difficult>0</difficult>
		<bndbox>
			<xmin>322.0</xmin>
			<ymin>34.0</ymin>
			<xmax>372.0</xmax>
			<ymax>84.0</ymax>
		</bndbox>
	</object>
	<object>
		<name>seals</name>
		<pose>Unspecified</pose>
		<truncated>0</truncated>
		<difficult>0</difficult>
		<bndbox>
			<xmin>329.0</xmin>
			<ymin>89.0</ymin>
			<xmax>379.0</xmax>
			<ymax>139.0</ymax>
		</bndbox>
	</object>
	<object>
		<name>seals</name>
		<pose>Unspecified</pose>
		<truncated>0</truncated>
		<difficult>0</difficult>
		<bndbox>
			<xmin>331.0</xmin>
			<ymin>116.0</ymin>
			<xmax>381.0</xmax>
			<ymax>166.0</ymax>
		</bndbox>
	</object>
	<object>
		<name>seals</name>
		<pose>Unspecified</pose>
		<truncated>0</truncated>
		<difficult>0</difficult>
		<bndbox>
			<xmin>336.0</xmin>
			<ymin>0.1</ymin>
			<xmax>386.0</xmax>
			<ymax>49.1</ymax>
		</bndbox>
	</object>
	<object>
		<name>seals</name>
		<pose>Unspecified</pose>
		<truncated>0</truncated>
		<difficult>0</difficult>
		<bndbox>
			<xmin>340.0</xmin>
			<ymin>195.0</ymin>
			<xmax>390.0</xmax>
			<ymax>245.0</ymax>
		</bndbox>
	</object>
	<object>
		<name>seals</name>
		<pose>Unspecified</pose>
		<truncated>0</truncated>
		<difficult>0</difficult>
		<bndbox>
			<xmin>341.0</xmin>
			<ymin>249.0</ymin>
			<xmax>391.0</xmax>
			<ymax>299.0</ymax>
		</bndbox>
	</object>
	<object>
		<name>seals</name>
		<pose>Unspecified</pose>
		<truncated>0</truncated>
		<difficult>0</difficult>
		<bndbox>
			<xmin>353.0</xmin>
			<ymin>0.1</ymin>
			<xmax>403.0</xmax>
			<ymax>39.1</ymax>
		</bndbox>
	</object>
	<object>
		<name>seals</name>
		<pose>Unspecified</pose>
		<truncated>0</truncated>
		<difficult>0</difficult>
		<bndbox>
			<xmin>353.0</xmin>
			<ymin>146.0</ymin>
			<xmax>403.0</xmax>
			<ymax>196.0</ymax>
		</bndbox>
	</object>
	<object>
		<name>seals</name>
		<pose>Unspecified</pose>
		<truncated>0</truncated>
		<difficult>0</difficult>
		<bndbox>
			<xmin>368.0</xmin>
			<ymin>103.0</ymin>
			<xmax>418.0</xmax>
			<ymax>153.0</ymax>
		</bndbox>
	</object>
	<object>
		<name>seals</name>
		<pose>Unspecified</pose>
		<truncated>0</truncated>
		<difficult>0</difficult>
		<bndbox>
			<xmin>370.0</xmin>
			<ymin>77.0</ymin>
			<xmax>420.0</xmax>
			<ymax>127.0</ymax>
		</bndbox>
	</object>
	<object>
		<name>seals</name>
		<pose>Unspecified</pose>
		<truncated>0</truncated>
		<difficult>0</difficult>
		<bndbox>
			<xmin>370.0</xmin>
			<ymin>309.0</ymin>
			<xmax>420.0</xmax>
			<ymax>359.0</ymax>
		</bndbox>
	</object>
	<object>
		<name>seals</name>
		<pose>Unspecified</pose>
		<truncated>0</truncated>
		<difficult>0</difficult>
		<bndbox>
			<xmin>380.0</xmin>
			<ymin>148.0</ymin>
			<xmax>430.0</xmax>
			<ymax>198.0</ymax>
		</bndbox>
	</object>
	<object>
		<name>seals</name>
		<pose>Unspecified</pose>
		<truncated>0</truncated>
		<difficult>0</difficult>
		<bndbox>
			<xmin>385.0</xmin>
			<ymin>239.0</ymin>
			<xmax>465.0</xmax>
			<ymax>319.0</ymax>
		</bndbox>
	</object>
	<object>
		<name>seals</name>
		<pose>Unspecified</pose>
		<truncated>0</truncated>
		<difficult>0</difficult>
		<bndbox>
			<xmin>393.0</xmin>
			<ymin>35.0</ymin>
			<xmax>443.0</xmax>
			<ymax>85.0</ymax>
		</bndbox>
	</object>
	<object>
		<name>seals</name>
		<pose>Unspecified</pose>
		<truncated>0</truncated>
		<difficult>0</difficult>
		<bndbox>
			<xmin>393.0</xmin>
			<ymin>173.0</ymin>
			<xmax>443.0</xmax>
			<ymax>223.0</ymax>
		</bndbox>
	</object>
	<object>
		<name>seals</name>
		<pose>Unspecified</pose>
		<truncated>0</truncated>
		<difficult>0</difficult>
		<bndbox>
			<xmin>418.0</xmin>
			<ymin>144.0</ymin>
			<xmax>468.0</xmax>
			<ymax>194.0</ymax>
		</bndbox>
	</object>
	<object>
		<name>seals</name>
		<pose>Unspecified</pose>
		<truncated>0</truncated>
		<difficult>0</difficult>
		<bndbox>
			<xmin>427.0</xmin>
			<ymin>54.0</ymin>
			<xmax>507.0</xmax>
			<ymax>134.0</ymax>
		</bndbox>
	</object>
	<object>
		<name>seals</name>
		<pose>Unspecified</pose>
		<truncated>0</truncated>
		<difficult>0</difficult>
		<bndbox>
			<xmin>432.0</xmin>
			<ymin>128.0</ymin>
			<xmax>482.0</xmax>
			<ymax>178.0</ymax>
		</bndbox>
	</object>
	<object>
		<name>seals</name>
		<pose>Unspecified</pose>
		<truncated>0</truncated>
		<difficult>0</difficult>
		<bndbox>
			<xmin>433.0</xmin>
			<ymin>85.0</ymin>
			<xmax>483.0</xmax>
			<ymax>135.0</ymax>
		</bndbox>
	</object>
	<object>
		<name>seals</name>
		<pose>Unspecified</pose>
		<truncated>0</truncated>
		<difficult>0</difficult>
		<bndbox>
			<xmin>438.0</xmin>
			<ymin>211.0</ymin>
			<xmax>488.0</xmax>
			<ymax>261.0</ymax>
		</bndbox>
	</object>
	<object>
		<name>seals</name>
		<pose>Unspecified</pose>
		<truncated>0</truncated>
		<difficult>0</difficult>
		<bndbox>
			<xmin>444.0</xmin>
			<ymin>17.0</ymin>
			<xmax>494.0</xmax>
			<ymax>67.0</ymax>
		</bndbox>
	</object>
	<object>
		<name>seals</name>
		<pose>Unspecified</pose>
		<truncated>0</truncated>
		<difficult>0</difficult>
		<bndbox>
			<xmin>444.0</xmin>
			<ymin>47.0</ymin>
			<xmax>494.0</xmax>
			<ymax>97.0</ymax>
		</bndbox>
	</object>
	<object>
		<name>seals</name>
		<pose>Unspecified</pose>
		<truncated>0</truncated>
		<difficult>0</difficult>
		<bndbox>
			<xmin>444.0</xmin>
			<ymin>115.0</ymin>
			<xmax>494.0</xmax>
			<ymax>165.0</ymax>
		</bndbox>
	</object>
	<object>
		<name>seals</name>
		<pose>Unspecified</pose>
		<truncated>0</truncated>
		<difficult>0</difficult>
		<bndbox>
			<xmin>445.0</xmin>
			<ymin>260.0</ymin>
			<xmax>495.0</xmax>
			<ymax>310.0</ymax>
		</bndbox>
	</object>
	<object>
		<name>seals</name>
		<pose>Unspecified</pose>
		<truncated>0</truncated>
		<difficult>0</difficult>
		<bndbox>
			<xmin>448.0</xmin>
			<ymin>228.0</ymin>
			<xmax>498.0</xmax>
			<ymax>278.0</ymax>
		</bndbox>
	</object>
	<object>
		<name>seals</name>
		<pose>Unspecified</pose>
		<truncated>0</truncated>
		<difficult>0</difficult>
		<bndbox>
			<xmin>454.0</xmin>
			<ymin>181.0</ymin>
			<xmax>504.0</xmax>
			<ymax>231.0</ymax>
		</bndbox>
	</object>
	<object>
		<name>seals</name>
		<pose>Unspecified</pose>
		<truncated>0</truncated>
		<difficult>0</difficult>
		<bndbox>
			<xmin>457.0</xmin>
			<ymin>93.0</ymin>
			<xmax>507.0</xmax>
			<ymax>143.0</ymax>
		</bndbox>
	</object>
	<object>
		<name>seals</name>
		<pose>Unspecified</pose>
		<truncated>0</truncated>
		<difficult>0</difficult>
		<bndbox>
			<xmin>472.0</xmin>
			<ymin>160.0</ymin>
			<xmax>522.0</xmax>
			<ymax>210.0</ymax>
		</bndbox>
	</object>
	<object>
		<name>seals</name>
		<pose>Unspecified</pose>
		<truncated>0</truncated>
		<difficult>0</difficult>
		<bndbox>
			<xmin>477.0</xmin>
			<ymin>105.0</ymin>
			<xmax>527.0</xmax>
			<ymax>155.0</ymax>
		</bndbox>
	</object></annotation>